rattlesnake/__init__.py
rattlesnake/hello.py
rattlesnake/rattlesnake.py
rattlesnake/cicd/__init__.py
rattlesnake/cicd/badge_color_coverage.py
rattlesnake/cicd/badge_color_pylint.py
rattlesnake/cicd/report_pylint.py
rattlesnake/cicd/report_pytest.py
rattlesnake/cicd/reports_main_page.py
rattlesnake/cicd/utilities.py
rattlesnake/components/__init__.py
rattlesnake/components/abstract_environment.py
rattlesnake/components/abstract_hardware.py
rattlesnake/components/abstract_message_process.py
rattlesnake/components/abstract_sysid_data_analysis.py
rattlesnake/components/abstract_sysid_environment.py
rattlesnake/components/acquisition.py
rattlesnake/components/data_collector.py
rattlesnake/components/data_physics_hardware.py
rattlesnake/components/data_physics_interface.py
rattlesnake/components/environments.py
rattlesnake/components/exodus_modal_solution_hardware.py
rattlesnake/components/lanxi_hardware_multiprocessing.py
rattlesnake/components/lanxi_stream.py
rattlesnake/components/modal_environment.py
rattlesnake/components/nidaqmx_hardware_multitask.py
rattlesnake/components/output.py
rattlesnake/components/random_vibration_sys_id_data_analysis.py
rattlesnake/components/random_vibration_sys_id_environment.py
rattlesnake/components/random_vibration_sys_id_utilities.py
rattlesnake/components/sdynpy_system_virtual_hardware.py
rattlesnake/components/signal_generation.py
rattlesnake/components/signal_generation_process.py
rattlesnake/components/skeleton_sys_id_environment.py
rattlesnake/components/spectral_processing.py
rattlesnake/components/state_space_virtual_hardware.py
rattlesnake/components/streaming.py
rattlesnake/components/time_environment.py
rattlesnake/components/transient_sys_id_environment.py
rattlesnake/components/ui_utilities.py
rattlesnake/components/user_interface.py
rattlesnake/components/utilities.py
rattlesnake_vibration_controller-3.0.2.dist-info/licenses/LICENSE
rattlesnake_vibration_controller-3.0.2.dist-info/METADATA
rattlesnake_vibration_controller-3.0.2.dist-info/WHEEL
rattlesnake_vibration_controller-3.0.2.dist-info/top_level.txt
rattlesnake_vibration_controller-3.0.2.dist-info/RECORD
