Metadata-Version: 2.4
Name: rattlesnake-vibration-controller
Version: 3.0.2
Summary: Multiple-Input Multiple-Output Vibration Controller
Author: Daniel P. Rohe
Author-email: dprohe@sandia.gov
License:                     GNU GENERAL PUBLIC LICENSE
Requires-Python: >=3.8
License-File: LICENSE
Requires-Dist: kaitaistruct
Requires-Dist: netCDF4
Requires-Dist: nidaqmx
Requires-Dist: numpy
Requires-Dist: openpyxl
Requires-Dist: PyQt5; sys_platform != "darwin"
Requires-Dist: PyQt6; sys_platform == "darwin"
Requires-Dist: pyqtgraph
Requires-Dist: qtpy
Requires-Dist: requests
Requires-Dist: scipy
Provides-Extra: dev
Requires-Dist: coverage-badge; extra == "dev"
Requires-Dist: flake8; extra == "dev"
Requires-Dist: isort; extra == "dev"
Requires-Dist: pylint; extra == "dev"
Requires-Dist: pytest; extra == "dev"
Requires-Dist: pytest-cov; extra == "dev"
Requires-Dist: pytest-qt==4.4.0; extra == "dev"
Requires-Dist: pytz; extra == "dev"
Requires-Dist: ruff; extra == "dev"
Dynamic: license-file
